Workbook

Sheet Leyenda
A1: Eventos del PDF "SimuladorSociales - Juego de Rol"
A3: Qué hay acá
B4: Los 67 eventos del PDF, transcritos completos: enunciado, respuestas, efectos, probabilidades y variaciones de stats. Una fila por EFECTO, que es la unidad más chica.
B5: Los minijuegos NO están en este archivo: quedan como están en el juego.
A7: De dónde sale cada evento
B8: La columna origen_pdf conserva la sección y el número del PDF (Generales 12, Guita 4, Historia 3) para poder volver al documento. Es solo trazabilidad.
B9: Por pedido tuyo, TODOS entran al juego como eventos generales: no se clasifican por guita / conocimiento / fama / política.
B10: La historia "El Cambio Social" del final del PDF está tomada como cinco eventos sueltos (Historia 1 a 5), sin encadenar.
A12: Cómo leer las columnas
A13: id | B13: EV01 a EV67. Agrupa las filas de un mismo evento.
A14: nivel | B14: Solo si el PDF lo aclara (Ingresante / Intermedio / Avanzado / Mitad de carrera). La mayoría viene vacío.
A15: n_resp | B15: Número de respuesta dentro del evento.
A16: n_efecto | B16: Número de efecto dentro de esa respuesta. Si hay más de uno, se sortea por probabilidad.
A17: probabilidad | B17: Del PDF. Los efectos de una misma respuesta suman 100%.
A18: guita ... politica | B18: Valor sugerido para cada stat. Vacío = el PDF no indica nada.
A19: notacion_pdf | B19: La notación literal del documento (+fama, --guita). Es la fuente; los números de al lado son una traducción.
A20: especial | B20: Marcado en amarillo. Cosas que no son un simple cambio de stats: minijuego, salida de carrera, termina partida, escalada de violencia, perdés un cuatrimestre, efectos condicionales.
A21: notas | B21: Aclaraciones sobre ambigüedades del PDF.
B28: Cuando el PDF da un número explícito (por ejemplo "-20 conocimiento" o "+3 de conocimiento") se respetó ese número y se aclaró en notas.
B29: Estos valores son una PROPUESTA: cambialos en las columnas de stats y el Resumen se actualiza solo.
A31: Qué falta decidir
B32: Hay eventos donde el PDF describe el resultado pero no asigna ninguna variación de stats. Quedaron con las cuatro columnas vacías, listos para que les pongas valor.
B33: Filtrá la hoja Eventos por guita/conocimiento/fama/politica vacíos para encontrarlos.
A35: La escala de puntos (actualizada)
B36: El PDF marca intensidad con signos, no con números. La escala vieja del juego era + = 5, ++ = 9, +++ = 14, pensada para partidas largas. Con solo 6 eventos por partida cada carta tiene que pesar mucho más, así que se multiplicó por 2,5:
A37: + / - | B37: 12 / -12
A38: ++ / -- | B38: 22 / -22
A39: +++ / --- | B39: 35 / -35
B40: Los números explícitos del PDF (+3, +5, -10, -20) se escalaron igual: quedan en 8, 12, -25 y -50.
A42: Balance de los cuatro stats
B43: Neto de cada uno sumando los 208 efectos: guita +30, conocimiento +40, fama +24, política +46. Proporcionalmente es el mismo equilibrio que antes de escalar; lo que importa es que ninguno quede muy por encima del resto.
B44: Los 109 valores del PDF venían torcidos: guita cerraba en -43 y política en +72 (en la escala vieja). Los 99 completados se usaron para emparejarlos.
A46: Arranque y bandas: hay que cambiarlos al cargar
B47: Simulando 30.000 partidas de 6 eventos con estos valores:
A48: arranque | B48: Los stats pasan a arrancar entre 40 y 60 (hoy es 24-36). Con saltos de 12 a 35 hace falta ese margen: si no, los stats se clavan en 0 y las últimas decisiones dejan de tener efecto.
A49: resultado | B49: Los stats terminan entre 10 y 91 (p5 y p95), con mediana 51. Solo el 2,5% queda clavado en 0 y otro 2,5% en 100.
A50: bandas | B50: Los cortes actuales (ALTA 40, BAJA 28) quedan obsoletos: con este arranque todos empezarían ya en ALTA. Los que mejor reparten son ALTA >= 60 y BAJA <= 36, o sea MEDIA de 37 a 59.
B51: Con esos cortes: 1 stat en alta 37,5% de las partidas, dupla 30,9%, trío 12,2%, ninguna en alta 17,7%, las cuatro en alta 1,6%. Muy parecido a lo que da el juego hoy.
B52: Nada de esto está en el Excel: son tres valores de db/contenido.js y db/seed.js que hay que tocar cuando se cargue el contenido.

Sheet Eventos
A1: id | B1: origen_pdf | C1: nivel | D1: titulo | E1: enunciado | F1: n_resp | G1: respuesta | H1: n_efecto | I1: probabilidad | J1: resultado | K1: guita | L1: conocimiento | M1: fama | N1: politica | O1: notacion_pdf | P1: origen_valores | Q1: especial | R1: notas
A2: EV01 | B2: Generales 1 | D2: David Lynch en la plaza seca | E2: Te quedás ranchando en la plaza seca y ves a una mina linda que nunca antes habías visto en tu vida. Un facuamigo te la presenta y resulta que los dos son fanáticos de David Lynch. Te enamorás profundamente. Al otro día tenés un coloquio en grupo importantísimo. Si no ponés de tu parte todo tu grupo se verá afectado. | F2: 1 | G2: Te quedás hasta las mil y una hablando con esta piba. Dios, Patria y Familia. En una de esas te terminás casando y se te resuelven la mitad de los problemas. Los compas sabrán entender. | H2: 1 | I2: 1 | J2: Los compas no supieron entender. | L2: -12 | M2: -12 | O2: -fama -conocimiento | P2: PDF
A3: EV01 | B3: Generales 1 | D3: David Lynch en la plaza seca | E3: Te quedás ranchando en la plaza seca y ves a una mina linda que nunca antes habías visto en tu vida. Un facuamigo te la presenta y resulta que los dos son fanáticos de David Lynch. Te enamorás profundamente. Al otro día tenés un coloquio en grupo importantísimo. Si no ponés de tu parte todo tu grupo se verá afectado. | F3: 2 | G3: Si es la indicada va a saber entender. Existe la posibilidad de que se corte el hechizo y no la veas más en tu vida. Intercambian instagrams. | H3: 1 | I3: 0.3 | J3: Resulta que era una militante de alternativa académica. Los abuelos tienen terrenos en la Pampa Húmeda. | K3: 12 | O3: +guita | P3: PDF | Q3: condicional | R3: En el PDF: si el jugador tiene guita pega onda (+guita); si no tiene un mango se le va la chance.
A4: EV01 | B4: Generales 1 | D4: David Lynch en la plaza seca | E4: Te quedás ranchando en la plaza seca y ves a una mina linda que nunca antes habías visto en tu vida. Un facuamigo te la presenta y resulta que los dos son fanáticos de David Lynch. Te enamorás profundamente. Al otro día tenés un coloquio en grupo importantísimo. Si no ponés de tu parte todo tu grupo se verá afectado. | F4: 2 | G4: Si es la indicada va a saber entender. Existe la posibilidad de que se corte el hechizo y no la veas más en tu vida. Intercambian instagrams. | H4: 2 | I4: 0.7 | J4: Se cortó el hechizo y no la viste nunca más. | N4: -12 | O4: -politica | P4: PDF
A5: EV02 | B5: Generales 2 | D5: El último bondi | E5: Te quedaste ranchando hasta cualquier hora con los pibes y vivís en Temperley. Llegás a la avenida y ves el último bondi que se te va. | F5: 1 | G5: Corrés el bondi. | H5: 1 | I5: 0.5 | J5: Llegás pero se te abrió la mochila y se te cayó todo. En el camino quedaron tus apuntes sobre Weber, Hobbes y Ofelia Fernández. Habrá que comenzar de nuevo. | K5: -12 | L5: -12 | O5: -conocimiento -guita | P5: PDF
A6: EV02 | B6: Generales 2 | D6: El último bondi | E6: Te quedaste ranchando hasta cualquier hora con los pibes y vivís en Temperley. Llegás a la avenida y ves el último bondi que se te va. | F6: 1 | G6: Corrés el bondi. | H6: 2 | I6: 0.5 | J6: Corrés el bondi pero te tropezás y caés. Te ayuda una chica que iba a subir pero se quedó preocupada por tu caída. Resulta que vive en la misma zona que vos y cursa T. S. Es el alma más noble que conociste en tu vida. Se van a tomar algo hasta cualquier hora. Quiere tus defectos más que tus virtudes (que no sobran). Contás la anécdota y tus amigos te cambian el apodo por Lilita Corrió. Tenés novia. | K6: -12 | L6: 12 | M6: 12 | O6: -guita +fama +conocimiento | P6: PDF
A7: EV02 | B7: Generales 2 | D7: El último bondi | E7: Te quedaste ranchando hasta cualquier hora con los pibes y vivís en Temperley. Llegás a la avenida y ves el último bondi que se te va. | F7: 2 | G7: No te apurás. Ya llegará otro. | H7: 1 | I7: 1 | J7: Estuviste tres horas esperando el bondi chupando frío. Te quisieron robar y las chicas que laburan en Consti saltaron por vos. Les contaste lo que estudiabas. Arrancás una movida contra la represión de la policía en el barrio contra las trabajadoras sexuales. | K7: -12 | M7: 12 | N7: 12 | O7: -guita +fama +politica | P7: PDF
A8: EV03 | B8: Generales 3 | D8: El que pide plata | E8: Entra una persona a pedir plata a la facultad. Dice que lo persigue Máximo Kirchner, que necesita plata para irse del país porque tiene información que puede llevar al arresto de la Dra. Cristina Fernández de Kirchner. | F8: 1 | G8: Le das plata. | H8: 1 | I8: 1 | J8: El tipo te agradece y dice que quiere mostrarte algo. Te lleva al baño. Tenés miedo pero lo seguís. "Acercate", susurra. Mete la mano por debajo del cuello y se saca una máscara: ¡es Nisman! | K8: -12 | N8: 12 | O8: -guita +politica | P8: PDF
A9: EV03 | B9: Generales 3 | D9: El que pide plata | E9: Entra una persona a pedir plata a la facultad. Dice que lo persigue Máximo Kirchner, que necesita plata para irse del país porque tiene información que puede llevar al arresto de la Dra. Cristina Fernández de Kirchner. | F9: 2 | G9: No le creés. | H9: 1 | I9: 1 | J9: El tipo se aleja sin problema. Antes de doblar la esquina un francotirador lo fulmina con un tiro en la frente. No llegás a ver de dónde dispararon pero hay humo en una ventana de la esquina de San José. | K9: 12 | M9: -12 | O9: +guita -fama | P9: PDF
A10: EV04 | B10: Generales 4 | D10: ¿Dónde vas a estudiar? | E10: Llegás temprano a la facultad por primera vez en tu vida. ¿A dónde vas a estudiar? | F10: 1 | G10: A la biblioteca. Obviamente. | H10: 1 | I10: 1 | J10: De tanto silencio te quedaste dormido. Llegaste tarde a la clase pero la siesta te hizo bien. Lo poco que estuviste participaste un montón. | L10: 12 | P10: propuesto
A11: EV04 | B11: Generales 4 | D11: ¿Dónde vas a estudiar? | E11: Llegás temprano a la facultad por primera vez en tu vida. ¿A dónde vas a estudiar? | F11: 2 | G11: Te encerrás en un aula vacía. | H11: 1 | I11: 1 | J11: A los quince minutos entró un grupo para una clase. Como te dio vergüenza te quedaste. Terminás aprendiendo mucho sobre Martín Lutero. | L11: 12 | P11: propuesto
A12: EV04 | B12: Generales 4 | D12: ¿Dónde vas a estudiar? | E12: Llegás temprano a la facultad por primera vez en tu vida. ¿A dónde vas a estudiar? | F12: 3 | G12: Agarrás una mesa en el foyer. | H12: 1 | I12: 1 | J12: Mala luz y letra minúscula. Entraste a cursar sin ver un pito. Encima no aprendiste un carajo. | L12: -12 | P12: propuesto
A13: EV05 | B13: Generales 5 | D13: Trabajo de investigación | E13: Tenés que hacer un trabajo de investigación en grupo. | F13: 1 | G13: Elegís el tema difícil. No solo se trata de aprobar la materia. Vas a aprender un montón. | H13: 1 | I13: 1 | J13: Le dedicás una banda de tiempo, queda bien y le gustó a la cátedra. | L13: 22 | P13: propuesto
A14: EV05 | B14: Generales 5 | D14: Trabajo de investigación | E14: Tenés que hacer un trabajo de investigación en grupo. | F14: 2 | G14: Elegís un tema papita que mucho no te interesa. Ese trabajo se va a redactar solo. | H14: 1 | I14: 1 | J14: Lo hiciste el día anterior. Te sacaste de encima la materia y fuiste a final. En el medio te hiciste nuevos facuamigos igual de vagos que vos. | L14: -12 | M14: 12 | P14: propuesto
A15: EV06 | B15: Generales 6 | D15: Clase muy embolante | E15: Clase muy embolante. | F15: 1 | G15: Dejás grabando el audio con el celular y te dormís. Si el profesor se da cuenta te podés ganar el odio para toda la cursada. | H15: 1 | I15: 0.5 | J15: El profesor se da cuenta. Te hace la vida imposible hasta el final. Recursás el cuatri siguiente pero en la otra cátedra. | L15: -22 | M15: -12 | P15: propuesto
A16: EV06 | B16: Generales 6 | D16: Clase muy embolante | E16: Clase muy embolante. | F16: 1 | G16: Dejás grabando el audio con el celular y te dormís. Si el profesor se da cuenta te podés ganar el odio para toda la cursada. | H16: 2 | I16: 0.5 | J16: El profesor se da cuenta pero le chupa un huevo. Es más, te ofrece un drive con los audios de todas las clases. Tu Samsung Pocket lo agradece. Con ese material aprendés un montón. | L16: 22 | P16: propuesto
A17: EV06 | B17: Generales 6 | D17: Clase muy embolante | E17: Clase muy embolante. | F17: 2 | G17: Te vas a comprar un café para remontarla. Es solo un mal momento. | H17: 1 | I17: 1 | J17: El exquisito café de las máquinas del CeXSo te hace efecto. La rompés. Y tan solo por 2000 pesos argensimios. | K17: -12 | L17: 12 | P17: propuesto
A18: EV06 | B18: Generales 6 | D18: Clase muy embolante | E18: Clase muy embolante. | F18: 3 | G18: Salís y hablás un rato con tu facuamigo que está haciendo tiempo. | H18: 1 | I18: 1 | J18: Te cuenta que va a ser papá y que los pañales están muy caros. Volvés y le metés con todo a la clase. En un futuro esos pañales no se van a pagar solos. | L18: 22 | P18: propuesto
A19: EV07 | B19: Generales 7 | D19: El que no para de decir boludeces | E19: Un pibe no para de decir boludeces en clase. El profesor ya no sabe cómo hacerle entender que está diciendo gansadas. | F19: 1 | G19: Te hacés cargo y tirás un "mejor escuchar la explicación del profesor". | H19: 1 | I19: 1 | J19: Los demás te lo agradecen y el profesor también, aunque quedás medio chupamedias. El pibe no volvió a acotar nunca más en su vida. | L19: 12 | M19: -12 | P19: propuesto
A20: EV07 | B20: Generales 7 | D20: El que no para de decir boludeces | E20: Un pibe no para de decir boludeces en clase. El profesor ya no sabe cómo hacerle entender que está diciendo gansadas. | F20: 2 | G20: No decís nada. La mejor forma de aprender es equivocándose. | H20: 1 | I20: 1 | J20: A la otra clase el pibe dejó la materia. | L20: 12 | P20: propuesto
A21: EV07 | B21: Generales 7 | D21: El que no para de decir boludeces | E21: Un pibe no para de decir boludeces en clase. El profesor ya no sabe cómo hacerle entender que está diciendo gansadas. | F21: 3 | G21: Agarrás el fierro caliente y le explicás lo que está diciendo mal. | H21: 1 | I21: 1 | J21: Vos también lo decís mal. El profesor abandona la cátedra por estar rodeado de pelotudos. Ahora es influencer de tarot marxista. | L21: -12 | M21: -12 | P21: propuesto
A22: EV08 | B22: Generales 8 | D22: ¿Por qué siguen acumulando? | E22: La profesora pregunta por qué los multimillonarios siguen acumulando pese a tener mucho dinero. | F22: 1 | G22: Para comer buena carne. | H22: 1 | I22: 1 | J22: Boca, Perón y El Diego. La solución a la globalización es el nacionalismo. | L22: -12 | M22: 12 | P22: propuesto
A23: EV08 | B23: Generales 8 | D23: ¿Por qué siguen acumulando? | E23: La profesora pregunta por qué los multimillonarios siguen acumulando pese a tener mucho dinero. | F23: 2 | G23: Hay que expropiarlos a todos. Buscar un por qué te chupa un huevo. | H23: 1 | I23: 1 | J23: Se notaron tus inclinaciones marxistas. | L23: -12 | N23: 12 | P23: propuesto
A24: EV08 | B24: Generales 8 | D24: ¿Por qué siguen acumulando? | E24: La profesora pregunta por qué los multimillonarios siguen acumulando pese a tener mucho dinero. | F24: 3 | G24: Para hacer fiestas gay con enanos. | H24: 1 | I24: 1 | J24: Quisiste hacer un chiste y no salió. Los demás te miraron medio raro. | M24: -12 | P24: propuesto
A25: EV08 | B25: Generales 8 | D25: ¿Por qué siguen acumulando? | E25: La profesora pregunta por qué los multimillonarios siguen acumulando pese a tener mucho dinero. | F25: 4 | G25: Porque no saben hacer otra cosa más que seguir el fetiche del dinero. | H25: 1 | I25: 1 | J25: A la profe le cerró bastante tu respuesta y te lo hace saber. Te motivás y mejorás tu desempeño. | L25: 22 | P25: propuesto
A26: EV09 | B26: Generales 9 | D26: El fan de Charles Manson | E26: Un compañero te cuenta que está fanatizado con Charles Manson, que era un incomprendido social y que lo que hizo estaba bien. | F26: 1 | G26: Ya se va a curar. Solo es medio raro. | H26: 1 | I26: 1 | J26: Mató a un cheto medio hippie de Comunicación Social. | M26: -12 | N26: -12 | P26: propuesto | Q26: violencia
A27: EV09 | B27: Generales 9 | D27: El fan de Charles Manson | E27: Un compañero te cuenta que está fanatizado con Charles Manson, que era un incomprendido social y que lo que hizo estaba bien. | F27: 2 | G27: Lo denunciás con las autoridades de la facultad. Se puede solucionar. | H27: 1 | I27: 1 | J27: Lo echan pero ni se entera de que fuiste vos. Ya lo sabía todo el mundo. | M27: 12 | N27: 12 | P27: propuesto
A28: EV09 | B28: Generales 9 | D28: El fan de Charles Manson | E28: Un compañero te cuenta que está fanatizado con Charles Manson, que era un incomprendido social y que lo que hizo estaba bien. | F28: 3 | G28: Armás un linchamiento sorpresa para tu amigo. La historia se repite... | H28: 1 | I28: 1 | J28: Se zarpan y lo matan. Mejor que ser oprimido. | M28: -12 | N28: -22 | P28: propuesto | Q28: violencia
A29: EV10 | B29: Generales 10 | D29: Final a las cinco de la tarde | E29: Tenés un final a las cinco de la tarde, tenés el día libre y no sabés nada. | F29: 1 | G29: Das la cara y sos sincero. Zafás y te ponen ausente o te comés un uno. | H29: 1 | I29: 0.5 | J29: Zafaste: te ponen ausente. | L29: -12 | P29: propuesto
A30: EV10 | B30: Generales 10 | D30: Final a las cinco de la tarde | E30: Tenés un final a las cinco de la tarde, tenés el día libre y no sabés nada. | F30: 1 | G30: Das la cara y sos sincero. Zafás y te ponen ausente o te comés un uno. | H30: 2 | I30: 0.5 | J30: Te comiste un uno. | L30: -22 | P30: propuesto
A31: EV10 | B31: Generales 10 | D31: Final a las cinco de la tarde | E31: Tenés un final a las cinco de la tarde, tenés el día libre y no sabés nada. | F31: 2 | G31: Te mirás un video motivacional de Locomotora Olivera, te tomás un mango loco, leés un resumen de sesenta páginas que conseguiste y salís a la cancha. | H31: 1 | I31: 0.8 | J31: Te fue como el orto, pero las ganas de comerte el mundo no te las saca nadie. | L31: -12 | M31: 12 | P31: propuesto
A32: EV10 | B32: Generales 10 | D32: Final a las cinco de la tarde | E32: Tenés un final a las cinco de la tarde, tenés el día libre y no sabés nada. | F32: 2 | G32: Te mirás un video motivacional de Locomotora Olivera, te tomás un mango loco, leés un resumen de sesenta páginas que conseguiste y salís a la cancha. | H32: 2 | I32: 0.2 | J32: La cafeína llegó al cerebro y saliste de la caverna así como decía Platón. Accediste a las Ideas y a partir de ahora creés en la Matrix. Te sacaste un 10. | L32: 22 | P32: propuesto
A33: EV11 | B33: Generales 11 | D33: El after y el Pity | E33: Cursás los sábados y no te quedan más faltas (sí, toman falta). El viernes salís pensando ir pasado de rosca a cursar, pero tu amigo consigue un after. Y está el Pity. | F33: 1 | G33: Me quedo libre pero conozco al Pity. Homero tiene más valor social que toda la obra de Talcott Parsons. La foto con él se la mostrás hasta a los perros. | H33: 1 | I33: 1 | J33: Quedaste libre. La foto con el Pity la tenés de fondo de pantalla. | L33: -12 | M33: 22 | P33: propuesto
A34: EV11 | B34: Generales 11 | D34: El after y el Pity | E34: Cursás los sábados y no te quedan más faltas (sí, toman falta). El viernes salís pensando ir pasado de rosca a cursar, pero tu amigo consigue un after. Y está el Pity. | F34: 2 | G34: Voy a cursar. No me queda otra. La próxima será. | H34: 1 | I34: 1 | J34: Fuiste a cursar. El Pity siguió existiendo sin vos. | L34: 12 | M34: -12 | P34: propuesto
A35: EV12 | B35: Generales 12 | D35: La sala de radio | E35: Pasás por la sala de radio y te das cuenta de que adentro hay dos del centro de estudiantes dándose masa. Tienen un candado aparte para asegurarse el telo. | F35: 1 | G35: Los mandás al frente. Corrés el riesgo de que sea para un trabajo práctico. | H35: 1 | I35: 1 | J35: Expusiste al CeXSo y a las autoridades. Para el estudiantado quedaste como el espía del amor. | M35: 12 | O35: +fama | P35: PDF
A36: EV12 | B36: Generales 12 | D36: La sala de radio | E36: Pasás por la sala de radio y te das cuenta de que adentro hay dos del centro de estudiantes dándose masa. Tienen un candado aparte para asegurarse el telo. | F36: 2 | G36: No soy vigilante. Además hay que subir la tasa de fecundidad. | H36: 1 | I36: 1 | J36: Sale a la luz por una foto. Era un curso intensivo con aproximación realista a la educación sexual. | K36: 0 | L36: 0 | M36: 0 | N36: 0 | P36: propuesto
A37: EV13 | B37: Generales 13 | D37: ¿Era linda? | E37: Le decís a tu novia que viste a una chica en la facultad que se parece a ella. Te pregunta si era linda. | F37: 1 | G37: Le decís que la chica era linda. | H37: 1 | I37: 1 | J37: Te puteó de arriba a abajo en el Burger, se podía escuchar a nenes llorando. Digamos que te quedaste sin novia y ni siquiera pudiste disfrutar de la hamburguesa. | M37: -12 | P37: propuesto
A38: EV13 | B38: Generales 13 | D38: ¿Era linda? | E38: Le decís a tu novia que viste a una chica en la facultad que se parece a ella. Te pregunta si era linda. | F38: 2 | G38: Le decís que la chica no era linda. | H38: 1 | I38: 1 | J38: Te puteó de arriba a abajo en el Burger, se podía escuchar a nenes llorando. Digamos que te quedaste sin novia y ni siquiera pudiste disfrutar de la hamburguesa. | M38: -12 | P38: propuesto | R38: En el PDF las dos respuestas tienen exactamente el mismo efecto. Es el chiste.
A39: EV14 | B39: Generales 14 | D39: Michael Jackson en la puerta | E39: Al salir de la facultad ves que hay un tipo vestido de Michael Jackson bailando y cantando. Al acercarte te dice "hee-hee". | F39: 1 | G39: Lo cagás a piñas. | H39: 1 | I39: 0.5 | J39: Tus compañeros no te pueden sacar de encima de Michael, se tuvo que meter la policía incluso. Otra denuncia más a la lista. | K39: -12 | O39: -guita | P39: PDF | Q39: violencia
A40: EV14 | B40: Generales 14 | D40: Michael Jackson en la puerta | E40: Al salir de la facultad ves que hay un tipo vestido de Michael Jackson bailando y cantando. Al acercarte te dice "hee-hee". | F40: 1 | G40: Lo cagás a piñas. | H40: 2 | I40: 0.5 | J40: No era un tipo vestido de Michael: era el verdadero Michael Jackson, que había venido a la Argentina en secreto. En los ojos del mundo quedás como un hijo de puta, peor que Chapman. | M40: -22 | N40: -22 | O40: --fama --politica | P40: PDF | Q40: violencia
A41: EV14 | B41: Generales 14 | D41: Michael Jackson en la puerta | E41: Al salir de la facultad ves que hay un tipo vestido de Michael Jackson bailando y cantando. Al acercarte te dice "hee-hee". | F41: 2 | G41: Lo retás a una competencia de baile. | H41: 1 | I41: 1 | J41: La facultad entera salió a ver este evento histórico. Le rompiste el ojete con la caminata lunar, el falso Michael se escapa furioso y ahora personas que no conocés te llaman "El Michael". | M41: 22 | O41: ++fama | P41: PDF | Q41: minijuego memotest (si ganás)
A42: EV14 | B42: Generales 14 | D42: Michael Jackson en la puerta | E42: Al salir de la facultad ves que hay un tipo vestido de Michael Jackson bailando y cantando. Al acercarte te dice "hee-hee". | F42: 2 | G42: Lo retás a una competencia de baile. | H42: 2 | I42: 1 | J42: Quedaste como un boludo. Hasta el profesor pelado que siempre tiene cara de culo se rió de lo mal que bailaste. Has cometido suicidio social. | M42: -35 | O42: ---fama | P42: PDF | Q42: minijuego memotest (si perdés)
A43: EV15 | B43: Generales 15 | D43: ¿Chorro o gil? | E43: En un recreo se acerca un tipo a tu ronda de amigos y te pregunta directamente: "¿vos sos chorro o gil?". | F43: 1 | G43: Sos chorro. | H43: 1 | I43: 1 | J43: "¿Vos chorro? Chorro de leche sos vos, gato." No te hace nada más que lastimar tus sentimientos y arruinarte el día, por lo que no pudiste escuchar el resto de la clase. | L43: -12 | O43: -conocimiento | P43: PDF
A44: EV15 | B44: Generales 15 | D44: ¿Chorro o gil? | E44: En un recreo se acerca un tipo a tu ronda de amigos y te pregunta directamente: "¿vos sos chorro o gil?". | F44: 2 | G44: Sos gil. | H44: 1 | I44: 0.5 | J44: Se te ríe en la cara, te empuja al piso y en un movimiento te roba a la wacha. (Si tenés novia, por este momento te corta.) | K44: -12 | M44: -12 | P44: propuesto | Q44: condicional
A45: EV15 | B45: Generales 15 | D45: ¿Chorro o gil? | E45: En un recreo se acerca un tipo a tu ronda de amigos y te pregunta directamente: "¿vos sos chorro o gil?". | F45: 2 | G45: Sos gil. | H45: 2 | I45: 0.5 | J45: Te agradece por la información y ves cómo va para el siguiente grupo: el chabón estaba recolectando datos para su tesis. | L45: 12 | P45: propuesto
A46: EV16 | B46: Generales 16 | D46: Sumate a ser un Therian | E46: Estás caminando por los pasillos de la facultad y ves un afiche pegado que dice "Sumate a ser un Therian". | F46: 1 | G46: Le sacás una foto y se la mandás a un amigo así se ríen juntos. | H46: 1 | I46: 1 | J46: Le mandás la foto a tu amigo y se ríe en demasía. Le causa tanta gracia el afiche que se lo manda a otra gente para que se rían también. De esta manera el afiche circula y le terminan haciendo alta publicidad a los therians. Sin darte cuenta la facultad se llena de ellos. | L46: -12 | P46: propuesto
A47: EV16 | B47: Generales 16 | D47: Sumate a ser un Therian | E47: Estás caminando por los pasillos de la facultad y ves un afiche pegado que dice "Sumate a ser un Therian". | F47: 2 | G47: Te metés en el grupo de therians para hacer un trabajo de investigación sobre cómo es la movida, aprender sus costumbres y, si es posible, destruirlos desde adentro. | H47: 1 | I47: 0.5 | J47: Entrás en el grupo creyéndote mejor que ellos pero de a poco vas entrando en la movida. Ahora vas al Barrio Chino los fines de semana disfrazado de lobo de las praderas. | L47: 12 | M47: -22 | P47: propuesto
A48: EV16 | B48: Generales 16 | D48: Sumate a ser un Therian | E48: Estás caminando por los pasillos de la facultad y ves un afiche pegado que dice "Sumate a ser un Therian". | F48: 2 | G48: Te metés en el grupo de therians para hacer un trabajo de investigación sobre cómo es la movida, aprender sus costumbres y, si es posible, destruirlos desde adentro. | H48: 2 | I48: 0.5 | J48: Una vez dentro del grupo se dan cuenta de que estás haciendo demasiadas preguntas y te descubren. Corrés para escapar y lo lográs, pero te amenazan diciéndote que si te vuelven a cruzar te muerden un pie. Al parecer la mafia de los therians es más poderosa de lo que creías: ahora caminás por la facultad con miedo. | M48: -12 | N48: -12 | P48: propuesto
A49: EV16 | B49: Generales 16 | D49: Sumate a ser un Therian | E49: Estás caminando por los pasillos de la facultad y ves un afiche pegado que dice "Sumate a ser un Therian". | F49: 3 | G49: Arrancás el afiche de la pared porque no te caben nada los therians. | H49: 1 | I49: 1 | J49: La mafia de los therians se da cuenta de que fuiste vos y en un descuido uno de ellos te mea los apuntes al mismo tiempo que ladra, como venganza. | L49: -12 | M49: -12 | P49: propuesto
A50: EV17 | B50: Generales 17 | D50: Las máquinas del kiosco | E50: Vas al kiosco en el recreo a comprarte un alfajor, un café, o lo que te alcance comprar con 2000 pesos. Llegás y te das cuenta de que reemplazaron a los que atienden por máquinas expendedoras. Las máquinas te parecen una garcha: no entendés cómo funcionan, solo aceptan Mercado Pago y vos tenés efectivo. | F50: 1 | G50: Le pedís a una mina que está comprando si te puede comprar un alfajor y vos le pasás efectivo. | H50: 1 | I50: 1 | J50: Te dice que con gusto te compraría un alfajor pero que no tiene plata en Mercado Pago: tenía 3 lucas y las gastó comprando unas Club Social. Al principio no sabés si creerle, pero te insiste con el mismo discurso hasta que ya se vuelve pesado el asunto. Te pide perdón como cinco veces. De todas maneras te convida unas Club Social y dice que está en deuda con vos. Te parece una reacción exagerada. | K50: 22 | P50: propuesto
A51: EV17 | B51: Generales 17 | D51: Las máquinas del kiosco | E51: Vas al kiosco en el recreo a comprarte un alfajor, un café, o lo que te alcance comprar con 2000 pesos. Llegás y te das cuenta de que reemplazaron a los que atienden por máquinas expendedoras. Las máquinas te parecen una garcha: no entendés cómo funcionan, solo aceptan Mercado Pago y vos tenés efectivo. | F51: 2 | G51: Te rebelás en contra del sistema, agarrás una silla de por ahí y la tirás contra el vidrio de las máquinas. | H51: 1 | I51: 0.5 | J51: Agarraste una silla, la tiraste al vidrio y no se rompió. Mierda que son resistentes esas máquinas. Encima se te quedaron viendo todos los que estaban ahí como si fueses un enfermo y nadie te bancó. Les decís que la silla se te cayó sin querer pero claramente no fue así. | M51: -22 | P51: propuesto | Q51: violencia
A52: EV17 | B52: Generales 17 | D52: Las máquinas del kiosco | E52: Vas al kiosco en el recreo a comprarte un alfajor, un café, o lo que te alcance comprar con 2000 pesos. Llegás y te das cuenta de que reemplazaron a los que atienden por máquinas expendedoras. Las máquinas te parecen una garcha: no entendés cómo funcionan, solo aceptan Mercado Pago y vos tenés efectivo. | F52: 2 | G52: Te rebelás en contra del sistema, agarrás una silla de por ahí y la tirás contra el vidrio de las máquinas. | H52: 2 | I52: 0.5 | J52: Agarrás la silla, la tirás contra una de las máquinas, el vidrio explota y das un discurso a los presentes sobre cómo el hombre tiene que enfrentarse ante la amenaza de las máquinas, el individualismo y la deshumanización. Conmovés a todo el mundo y te volvés un nuevo referente político. Ahora sos leyenda. | N52: 22 | P52: propuesto | Q52: violencia
A53: EV17 | B53: Generales 17 | D53: Las máquinas del kiosco | E53: Vas al kiosco en el recreo a comprarte un alfajor, un café, o lo que te alcance comprar con 2000 pesos. Llegás y te das cuenta de que reemplazaron a los que atienden por máquinas expendedoras. Las máquinas te parecen una garcha: no entendés cómo funcionan, solo aceptan Mercado Pago y vos tenés efectivo. | F53: 3 | G53: No comprás una mierda. | H53: 1 | I53: 1 | J53: Volvés a la clase después del recreo y te pinta el sueño de golpe. No comiste nada y sentís que tu vida es una mierda. Entrás en una crisis existencial y no prestaste nada de atención en la clase. Encima ahora estás re angustiado. | K53: 22 | L53: -12 | P53: propuesto
A54: EV18 | B54: Generales 18 | D54: El que no para de hablar | E54: Llegás temprano a la cursada, antes de que arranque la clase, y no conocés a nadie. Estás esperando tranqui y se te acerca un loco a sacarte charla. Al principio te cae bien, pero después te rescatás de que es medio boludo y ahora no te para de hablar en la mitad de la clase. | F54: 1 | G54: Le decís que se calle, que querés prestar atención a la clase. | H54: 1 | I54: 1 | J54: El chabón piensa que lo estás jodiendo y sigue hablando. Se lo volvés a repetir y se le parte el corazón: se pone a llorar en mitad de la clase y los otros estudiantes te miran como si fuera tu culpa. | L54: 12 | M54: -12 | O54: -fama +conocimiento | P54: PDF
A55: EV18 | B55: Generales 18 | D55: El que no para de hablar | E55: Llegás temprano a la cursada, antes de que arranque la clase, y no conocés a nadie. Estás esperando tranqui y se te acerca un loco a sacarte charla. Al principio te cae bien, pero después te rescatás de que es medio boludo y ahora no te para de hablar en la mitad de la clase. | F55: 2 | G55: Te sumás a la charla, total estás hasta los huevos de la clase. | H55: 1 | I55: 1 | J55: Le seguís el juego y el chabón te cuenta que está organizando una redada contra los therians. Ellos son tus enemigos, así que el enemigo de tu enemigo es tu amigo. | L55: -12 | P55: propuesto
A56: EV18 | B56: Generales 18 | D56: El que no para de hablar | E56: Llegás temprano a la cursada, antes de que arranque la clase, y no conocés a nadie. Estás esperando tranqui y se te acerca un loco a sacarte charla. Al principio te cae bien, pero después te rescatás de que es medio boludo y ahora no te para de hablar en la mitad de la clase. | F56: 3 | G56: No le respondés a ninguna de sus intervenciones esperando que se calle de una vez. | H56: 1 | I56: 1 | J56: El chabón no se calla. No tiene drama con que vos no hables: quiere hacer un monólogo. Te estuvo hablando toda la clase y no pudiste prestar atención. | L56: -12 | P56: propuesto
A57: EV19 | B57: Generales 19 | D57: El profesor en la calle | E57: Un día como cualquier otro estás caminando por la calle y te das cuenta de que enfrente tuyo está un profesor de la facu. No sabés si saludarlo o no, porque dudás de si el chabón te conoce: vos no participás mucho en clase y él tiene una banda de alumnos. | F57: 1 | G57: Lo saludás. | H57: 1 | I57: 1 | J57: Lo saludás de prepo y te mira raro. Después le explicás que sos alumno suyo y parece no importarle mucho: te dice que prefiere no mezclar su vida profesional con su vida privada y te pide por favor que te vayas. | M57: -12 | P57: propuesto
A58: EV19 | B58: Generales 19 | D58: El profesor en la calle | E58: Un día como cualquier otro estás caminando por la calle y te das cuenta de que enfrente tuyo está un profesor de la facu. No sabés si saludarlo o no, porque dudás de si el chabón te conoce: vos no participás mucho en clase y él tiene una banda de alumnos. | F58: 2 | G58: Lo mirás, te mira, agachás la cabeza, lo volvés a mirar, te mira, lo saludás pero baja la cabeza, cortás el saludo sin llegar a terminarlo. | H58: 1 | I58: 1 | J58: Ninguno de los dos sabe si lo saludaste o no. Menos 1000 de aura. | M58: -22 | P58: propuesto
A59: EV19 | B59: Generales 19 | D59: El profesor en la calle | E59: Un día como cualquier otro estás caminando por la calle y te das cuenta de que enfrente tuyo está un profesor de la facu. No sabés si saludarlo o no, porque dudás de si el chabón te conoce: vos no participás mucho en clase y él tiene una banda de alumnos. | F59: 3 | G59: No lo saludás. | H59: 1 | I59: 1 | J59: Notás que te mira y vos no lo saludás. Sucede todo muy rápido. En la próxima clase, antes de entrar al aula, te cruza y te dice: "¿qué pasa, dormimos juntos?". Parece que te reconoció y no se tomó bien que no lo saludes. | M59: -12 | P59: propuesto
A60: EV20 | B60: Generales 20 | D60: La madriguera de los therians | E60: El loco que te habló durante toda la clase te dice que está listo para atacar a los therians. Te pide ayuda. | F60: 1 | G60: Lo seguís. | H60: 1 | I60: 1 | J60: Los therians se encuentran en un aula del subsuelo que bautizaron "la madriguera". Vas ahí con el loco y se desata una batalla. Los therians son muy poderosos y parece que van a triunfar, pero el loco saca un silbato para perros. Lo hace sonar y logra adiestrarlos: ahora son tus secuaces. | M60: 12 | N60: 12 | P60: propuesto | Q60: violencia
A61: EV20 | B61: Generales 20 | D61: La madriguera de los therians | E61: El loco que te habló durante toda la clase te dice que está listo para atacar a los therians. Te pide ayuda. | F61: 2 | G61: No lo seguís. | H61: 1 | I61: 1 | J61: El loco se manda solo contra los therians. Lo destrozan y suman fuerza en la facultad. Cada vez son más poderosos y ahora corrés un peligro mayor. | M61: -12 | N61: -12 | P61: propuesto
A62: EV21 | B62: Generales 21 | D62: Parcial mañana, once de la noche | E62: Mañana tenés un parcial y sentís que no estudiaste lo suficiente. Son las once de la noche y tenés algo de sueño. | F62: 1 | G62: Le pegás derecho toda la noche, hay que aprobar. | H62: 1 | I62: 1 | J62: Estudiaste toda la noche y llegás al parcial con veinte minutos de sueño. Te dan las consignas pero tu cerebro no funciona. Empezás a tener delirios con que uno de tus compañeros te quiere atacar y le pegás una cachetada. Nadie entiende lo que pasó y te retirás sobrepasado por la situación. | L62: -22 | M62: -12 | P62: propuesto | Q62: violencia
A63: EV21 | B63: Generales 21 | D63: Parcial mañana, once de la noche | E63: Mañana tenés un parcial y sentís que no estudiaste lo suficiente. Son las once de la noche y tenés algo de sueño. | F63: 2 | G63: Te vas a dormir. Mejor estar descansado durante el parcial. | H63: 1 | I63: 1 | J63: Llegás con la cabeza despejada pero sin tener tan en claro los conceptos. Igual algo de idea tenés. Son cinco preguntas: una la sabés bien y tres a medias. Te quedás dos horas chamuyando a lo loco y aprobás de pedo. | L63: 12 | P63: propuesto
A64: EV21 | B64: Generales 21 | D64: Parcial mañana, once de la noche | E64: Mañana tenés un parcial y sentís que no estudiaste lo suficiente. Son las once de la noche y tenés algo de sueño. | F64: 3 | G64: Le hablás a la IA y le decís que te haga un repaso de los temas del parcial y estudiás de ahí. | H64: 1 | I64: 1 | J64: Te quedás un rato a la noche estudiando con la IA. Al otro día caés al parcial, te dan la hoja y te las sabés todas: esto lo resolvés de taquito. A la semana te llega la nota y te sacaste un 2. La IA te dijo cualquier data. | L64: -22 | P64: propuesto
A65: EV22 | B65: Generales 22 | D65: La jauría en el patio gay | E65: Un día estás tomándote un café de tranquis en el patio gay y la jauría de therians se presenta, hace contacto visual y se dirige hacia vos. | F65: 1 | G65: Corrés por tu vida. | H65: 1 | I65: 1 | J65: Los therians son más rápidos: te alcanzan y te mean todo, a vos y a tu mochila. Te rompen los apuntes y quedás como la perrita de los therians frente a toda la facu. | L65: -12 | M65: -22 | P65: propuesto
A66: EV22 | B66: Generales 22 | D66: La jauría en el patio gay | E66: Un día estás tomándote un café de tranquis en el patio gay y la jauría de therians se presenta, hace contacto visual y se dirige hacia vos. | F66: 2 | G66: Te enfrentás. | H66: 1 | I66: 1 | J66: Te parás de mano pero son muy fuertes. Te rasguñan toda la cara pero te la bancás. Lográs ganarles y quedás como el capo que se cogió a los therians. | M66: 22 | P66: propuesto | Q66: violencia
A67: EV22 | B67: Generales 22 | D67: La jauría en el patio gay | E67: Un día estás tomándote un café de tranquis en el patio gay y la jauría de therians se presenta, hace contacto visual y se dirige hacia vos. | F67: 3 | G67: Te hacés pasar por uno de ellos. | H67: 1 | I67: 1 | J67: Los therians, confundidos, no saben qué hacer. Se miran entre ellos y deciden dejarte en paz. Parece que te libraste de ellos. | L67: 12 | P67: propuesto
A68: EV23 | B68: Generales 23 | D68: Inscripciones por el SIU | E68: Mañana son las inscripciones del cuatrimestre por el SIU Guaraní y no sabés bien a qué materia inscribirte ni con qué personas. | F68: 1 | G68: Te inscribís a una materia con la chica que te gusta. | H68: 1 | I68: 1 | J68: En la materia hay que hacer un trabajo de a dos durante toda la cursada. Armás grupo con la piba y tenés la oportunidad de conocerla mejor. Ella dice estar muy ocupada y vos te matás haciendo el 90% del trabajo porque sos un boludo. Logran aprobar y la invitás a salir: te rechaza diciendo que prefiere preservar la amistad. Por lo menos te re curtiste y te quedaron re claros los conceptos de la materia. | L68: 22 | M68: -12 | P68: propuesto
A69: EV23 | B69: Generales 23 | D69: Inscripciones por el SIU | E69: Mañana son las inscripciones del cuatrimestre por el SIU Guaraní y no sabés bien a qué materia inscribirte ni con qué personas. | F69: 2 | G69: Coordinás con un amigo para inscribirse a la misma materia. | H69: 1 | I69: 1 | J69: Dan la materia juntos y ninguno de los dos caza una. Desaprueban los parciales pero aprueban los recuperatorios raspando. Llegan a final y los dos aprueban con 5. Un éxito la cursada. | L69: 12 | P69: propuesto
A70: EV23 | B70: Generales 23 | D70: Inscripciones por el SIU | E70: Mañana son las inscripciones del cuatrimestre por el SIU Guaraní y no sabés bien a qué materia inscribirte ni con qué personas. | F70: 3 | G70: Te inscribís a la que querés dar, que la chupen los demás. | H70: 1 | I70: 1 | J70: Te inscribís por tu cuenta, si no se te traban las correlativas. Un pijazo cursar solo, pero te hacés nuevos amigos uno más boludo que el otro. Le metés con todo a la materia y promocionás. | L70: 22 | M70: 12 | P70: propuesto
A71: EV24 | B71: Generales 24 | D71: Llueve y hay mate en el buffet | E71: Salís al recreo con unos nuevos facuamigos que hiciste en una clase sumamente aburrida. Están en el buffet tomando mate, afuera llueve, y tenés que volver a la clase. | F71: 1 | G71: Volvés a la clase. | H71: 1 | I71: 1 | J71: Justo explicaron un tema súper importante que entra en el parcial, así que agradecés haber vuelto. Lo único malo es que no podés más con tu vida del aburrimiento y estás esperando morir. | L71: 12 | P71: propuesto
A72: EV24 | B72: Generales 24 | D72: Llueve y hay mate en el buffet | E72: Salís al recreo con unos nuevos facuamigos que hiciste en una clase sumamente aburrida. Están en el buffet tomando mate, afuera llueve, y tenés que volver a la clase. | F72: 2 | G72: Quedarte hablando con tus compañeros. | H72: 1 | I72: 1 | J72: Te quedaste hablando con los compas sobre anécdotas marihuaneras. Pegaste buena onda con tus nuevos amigos, conseguiste nota de brownies locos a 5 lucas y los pibes se rieron de aquella vez en que, estando re loco, después de bañarte pusiste la toalla en el perchero y la campera donde va la toalla. | K72: -12 | L72: -12 | M72: 12 | P72: propuesto
A73: EV24 | B73: Generales 24 | D73: Llueve y hay mate en el buffet | E73: Salís al recreo con unos nuevos facuamigos que hiciste en una clase sumamente aburrida. Están en el buffet tomando mate, afuera llueve, y tenés que volver a la clase. | F73: 3 | G73: Quedarte un rato hablando y volver tarde a la clase. | H73: 1 | I73: 1 | J73: Te quedás un rato más y decidís que es momento de volver. Los pibes deciden seguirte y ahora parece que sos el líder. Te perdiste la introducción a un tema importante que va para el parcial, pero más o menos cazaste la idea. | L73: -12 | M73: 12 | P73: propuesto
A74: EV25 | B74: Generales 25 | D74: ¿A qué hora ponés la alarma? | E74: Volvés a tu casa después de un recital a las 3 de la mañana y tenés que estar a las 8 en la facu. Teniendo en cuenta que tenés como una hora de viaje, no vas a dormir mucho. ¿A qué hora ponés la alarma? | F74: 1 | G74: No pongo ninguna alarma, me quedo durmiendo. | H74: 1 | I74: 1 | J74: Te quedás durmiendo. Hablás con un compañero para preguntarle qué hicieron y te dice que la clase duró media hora nada más, porque al profe le agarró una hemorragia nasal y hubo que suspenderla. Rarísimo, pero bueno: agradecés no haber ido. | K74: 22 | P74: propuesto
A75: EV25 | B75: Generales 25 | D75: ¿A qué hora ponés la alarma? | E75: Volvés a tu casa después de un recital a las 3 de la mañana y tenés que estar a las 8 en la facu. Teniendo en cuenta que tenés como una hora de viaje, no vas a dormir mucho. ¿A qué hora ponés la alarma? | F75: 2 | G75: Pongo la alarma a las 7 y llego re tarde. Me chupa un huevo ser puntual. | H75: 1 | I75: 1 | J75: Llegás una hora tarde, vas para el aula y no hay nadie. Te cruzás a un compañero y te dice que suspendieron la clase porque al profe le agarró una hemorragia nasal incontrolable. Rarísimo pero real. Fuiste a la facultad al pedo, tenés sueño, depresión, y toca enfrentar la vuelta a casa. | K75: -12 | L75: -12 | P75: propuesto
A76: EV25 | B76: Generales 25 | D76: ¿A qué hora ponés la alarma? | E76: Volvés a tu casa después de un recital a las 3 de la mañana y tenés que estar a las 8 en la facu. Teniendo en cuenta que tenés como una hora de viaje, no vas a dormir mucho. ¿A qué hora ponés la alarma? | F76: 3 | G76: Pongo varias alarmas para que suenen cada dos minutos a partir de las 6:15. | H76: 1 | I76: 1 | J76: Increíblemente llegás temprano. Por alguna razón que no entendés te sentás en la primera fila, enfrente del profesor. Estás haciendo fuerza para mantenerte despierto y a la media hora le empieza a sangrar la nariz al profe, pero heavy, y te empieza a salpicar en la cara así bien gore. Le ofrecés unos pañuelitos y él te lo agradece. | L76: 22 | P76: propuesto
A77: EV26 | B77: Generales 26 | D77: El campamento anticapitalista | E77: Te invitan a participar del campamento anticapitalista. | F77: 1 | G77: No curtís con esa. | H77: 1 | I77: 1 | J77: Les cortaste el rostro y no los dejaste hablar. | M77: -12 | N77: -12 | P77: propuesto
A78: EV26 | B78: Generales 26 | D78: El campamento anticapitalista | E78: Te invitan a participar del campamento anticapitalista. | F78: 2 | G78: ¡Oh sí! Me encantan los campamentos. | H78: 1 | I78: 1 | J78: Fuiste, hiciste Tiktoks, mojaste las patas en una pelopincho, y escuchaste ochenta y tres razones por las que el capitalismo no va más. | L78: -12 | M78: 12 | P78: propuesto
A79: EV26 | B79: Generales 26 | D79: El campamento anticapitalista | E79: Te invitan a participar del campamento anticapitalista. | F79: 3 | G79: Vas escéptico para hacer un poco de observación participante | H79: 1 | I79: 1 | J79: Viste la dinámica y te pareció dudoso el ímpetu del movimiento. Todos los militantes parecían cyborgs. Investigaste más y encontraste una relación entre la agrupación y el Mossad pero te enamoraste de unx cyborg anticapitalista. Van a tener hijes anticapitalistas. | L79: 22 | N79: -12 | P79: propuesto
A80: EV27 | B80: Generales 27 | D80: La marcha universitaria | E80: Convocan a la vigésima marcha universitaria. Los docentes y no docentes cobran una miseria y no cumplen la ley universitaria que votó el Congreso. | F80: 1 | G80: Vamos a la marcha, Jesse. | H80: 1 | I80: 1 | J80: Te cruzaste a El Momo dando una nota. Fotito, arroba y story para Instagram. Te hiciste viral. El mejor día de tu vida. | M80: 22 | N80: 12 | P80: propuesto
A81: EV27 | B81: Generales 27 | D81: La marcha universitaria | E81: Convocan a la vigésima marcha universitaria. Los docentes y no docentes cobran una miseria y no cumplen la ley universitaria que votó el Congreso. | F81: 2 | G81: Me quedo estudiando para la materia. | H81: 1 | I81: 1 | J81: Te perdiste de la efervescencia social. Aprobaste pero te miran raro. | L81: 12 | M81: -12 | N81: -12 | P81: propuesto
A82: EV27 | B82: Generales 27 | D82: La marcha universitaria | E82: Convocan a la vigésima marcha universitaria. Los docentes y no docentes cobran una miseria y no cumplen la ley universitaria que votó el Congreso. | F82: 3 | G82: Vagos de mierda, vayan a laburar. | H82: 1 | I82: 1 | J82: Sos un pelotudo. Sí, sos un pelotudo. | M82: -12 | N82: -22 | P82: propuesto
A83: EV28 | B83: Generales 28 | D83: El médico te receta anteojos | E83: El médico te receta anteojos. | F83: 1 | G83: No le das bola. No gastás guita en eso. | H83: 1 | I83: 1 | J83: Ves borroso y confundís a la profe con tu amiga: "esta vieja de mierda no para de romper las bolas". Perdiste aura. | K83: 22 | L83: -12 | M83: -12 | P83: propuesto
A84: EV28 | B84: Generales 28 | D84: El médico te receta anteojos | E84: El médico te receta anteojos. | F84: 2 | G84: Vas y te comprás unos en la feria. | H84: 1 | I84: 1 | J84: Te brindan poderes astrológicos que te permiten ver más allá de la suma de individualidades. Ahora comprendés Helechos Sociales. | K84: -12 | L84: 12 | P84: propuesto
A85: EV28 | B85: Generales 28 | D85: El médico te receta anteojos | E85: El médico te receta anteojos. | F85: 3 | G85: Ponés toda la teca y te preservás. | H85: 1 | I85: 1 | J85: Rendimiento óptimo. Tom Cruise en Misión Imposible. Leés el I Ching. | K85: -12 | L85: 22 | P85: propuesto
A86: EV29 | B86: Generales 29 | D86: El argentino más importante | E86: Se te acercan las de Comu y te preguntan cuál es el argentino más importante de la historia. | F86: 1 | G86: Favaloro. | H86: 1 | I86: 1 | J86: Leíste Qué es el radicalismo, de Alfonsín. | L86: 12 | P86: propuesto
A87: EV29 | B87: Generales 29 | D87: El argentino más importante | E87: Se te acercan las de Comu y te preguntan cuál es el argentino más importante de la historia. | F87: 2 | G87: El Che. | H87: 1 | I87: 1 | J87: Te gusta el bardo. Te la bancás. | N87: 12 | P87: propuesto
A88: EV29 | B88: Generales 29 | D88: El argentino más importante | E88: Se te acercan las de Comu y te preguntan cuál es el argentino más importante de la historia. | F88: 3 | G88: San Martín. | H88: 1 | I88: 1 | J88: Fuiste a la segura. No sumás ni restás. | K88: 0 | L88: 0 | M88: 0 | N88: 0 | P88: propuesto
A89: EV29 | B89: Generales 29 | D89: El argentino más importante | E89: Se te acercan las de Comu y te preguntan cuál es el argentino más importante de la historia. | F89: 4 | G89: El Diego. | H89: 1 | I89: 1 | J89: EL IIIEEEEGOOOOOOOOOOO. | M89: 22 | P89: propuesto
A90: EV30 | B90: Generales 30 | D90: Estás fusilado | E90: Estás fusilado y cursás hasta la noche. Querés dormir un rato. | F90: 1 | G90: Siestario en HU400. | H90: 1 | I90: 1 | J90: Te quedó el cuello como un acordeón. En medio de la clase soñaste que te cortaba la cabeza Robespierre. | L90: -12 | P90: propuesto
A91: EV30 | B91: Generales 30 | D91: Estás fusilado | E91: Estás fusilado y cursás hasta la noche. Querés dormir un rato. | F91: 2 | G91: Plaza seca al sol. | H91: 1 | I91: 1 | J91: Diez minutos y nada más. Mucho ruido para seguir. Una nutritiva siesta intelectual. | L91: 12 | P91: propuesto
A92: EV30 | B92: Generales 30 | D92: Estás fusilado | E92: Estás fusilado y cursás hasta la noche. Querés dormir un rato. | F92: 3 | G92: Te encerrás en un aula. | H92: 1 | I92: 1 | J92: Entran tres personas y se disculpan pensando que sos profesor. No descansaste una mierda pero sumaste confianza. | M92: 12 | P92: propuesto
A93: EV31 | B93: Generales 31 | D93: Entra un grupo armado | E93: Entra un grupo armado a la facultad. Tienen brazaletes y bigotes que conocés. | F93: 1 | G93: Confrontás y ponés el pecho. | H93: 1 | I93: 0.5 | J93: Terminaron a las piñas. Uno de ellos tiró y te dio en la panza. Moriste siendo defensor de la universidad pública. Murales, remeras, canciones: nunca más van a olvidar tu nombre. | M93: 35 | N93: 22 | P93: propuesto | Q93: termina partida / violencia
A94: EV31 | B94: Generales 31 | D94: Entra un grupo armado | E94: Entra un grupo armado a la facultad. Tienen brazaletes y bigotes que conocés. | F94: 1 | G94: Confrontás y ponés el pecho. | H94: 2 | I94: 0.5 | J94: Piñas. Se armó una muchedumbre en su contra. Uno tiró y mató a uno. Podrías haber sido vos. Te convertís en referente de un movimiento que lo recuerda. Te encargás de que nunca se olvide su nombre. | M94: 12 | N94: 22 | P94: propuesto | Q94: violencia
A95: EV31 | B95: Generales 31 | D95: Entra un grupo armado | E95: Entra un grupo armado a la facultad. Tienen brazaletes y bigotes que conocés. | F95: 2 | G95: Salís y llamás a la policía. No volvés a la facultad hasta que se resuelva la situación. | H95: 1 | I95: 1 | J95: Soldado que huye sirve para otra guerra. Pero qué cagón que sos. | M95: -12 | N95: -12 | P95: propuesto
A96: EV31 | B96: Generales 31 | D96: Entra un grupo armado | E96: Entra un grupo armado a la facultad. Tienen brazaletes y bigotes que conocés. | F96: 3 | G96: Empezás a gritar como loquita. | H96: 1 | I96: 1 | J96: Solamente aportaste banda sonora a la situación. | M96: -12 | P96: propuesto
A97: EV32 | B97: Generales 32 | D97: Jueves de feria | E97: Es jueves de feria y te cruzás con una tanga de CRISTINA LIBRE. | F97: 1 | G97: Comprás. | H97: 1 | I97: 1 | J97: Hay que prender fuego Clarín. | K97: -12 | N97: 12 | P97: propuesto
A98: EV32 | B98: Generales 32 | D98: Jueves de feria | E98: Es jueves de feria y te cruzás con una tanga de CRISTINA LIBRE. | F98: 2 | G98: No comprás. | H98: 1 | I98: 1 | J98: Muere una flequilluda con campera de Adidas. | K98: 22 | N98: -12 | P98: propuesto
A99: EV33 | B99: Guita 1 | D99: Turno noche en la hamburguesería | E99: Te ofrecen un trabajo nocturno en una cadena muy conocida de hamburguesas. Por el horario capaz que hasta podés comerte alguna. | F99: 1 | G99: Aceptás el laburo. | H99: 1 | I99: 0.75 | J99: Ganás plata pero estás más cansado y perdés horas de cursada. Con lo recaudado comprás sanguchitos y café en el buffet. | K99: 12 | L99: -12 | O99: +guita -conocimiento | P99: PDF | R99: El PDF también marca -Energía, un stat que el juego no tiene.
A100: EV33 | B100: Guita 1 | D100: Turno noche en la hamburguesería | E100: Te ofrecen un trabajo nocturno en una cadena muy conocida de hamburguesas. Por el horario capaz que hasta podés comerte alguna. | F100: 1 | G100: Aceptás el laburo. | H100: 2 | I100: 0.25 | J100: Hacés una monografía para una materia contando el sistema de cooperación entre compañeros en el espacio de trabajo. Te ganaste el aplauso de los profesores y sumás puntos académicos. | L100: 8 | O100: conocimiento:3 | P100: PDF | R100: El PDF dice +3 de conocimiento.
...

Sheet Resumen
A1: id | B1: origen_pdf | C1: nivel | D1: titulo | E1: respuestas | F1: efectos | G1: suma guita | H1: suma conocimiento | I1: suma fama | J1: suma politica | K1: especiales
A2: EV01 | B2: Generales 1 | D2: David Lynch en la plaza seca | E2: =COUNTIFS(Eventos!$A$2:$A$209,$A2,Eventos!$H$2:$H$209,1) -> 2 | F2: =COUNTIF(Eventos!$A$2:$A$209,$A2) -> 3 | G2: =SUMIF(Eventos!$A$2:$A$209,$A2,Eventos!$K$2:$K$209) -> 12 | H2: =SUMIF(Eventos!$A$2:$A$209,$A2,Eventos!$L$2:$L$209) -> -12 | I2: =SUMIF(Eventos!$A$2:$A$209,$A2,Eventos!$M$2:$M$209) -> -12 | J2: =SUMIF(Eventos!$A$2:$A$209,$A2,Eventos!$N$2:$N$209) -> -12 | K2: =COUNTIFS(Eventos!$A$2:$A$209,$A2,Eventos!$Q$2:$Q$209,"<>") -> 1
A3: EV02 | B3: Generales 2 | D3: El último bondi | E3: =COUNTIFS(Eventos!$A$2:$A$209,$A3,Eventos!$H$2:$H$209,1) -> 2 | F3: =COUNTIF(Eventos!$A$2:$A$209,$A3) -> 3 | G3: =SUMIF(Eventos!$A$2:$A$209,$A3,Eventos!$K$2:$K$209) -> -36 | H3: =SUMIF(Eventos!$A$2:$A$209,$A3,Eventos!$L$2:$L$209) -> 0 | I3: =SUMIF(Eventos!$A$2:$A$209,$A3,Eventos!$M$2:$M$209) -> 24 | J3: =SUMIF(Eventos!$A$2:$A$209,$A3,Eventos!$N$2:$N$209) -> 12 | K3: =COUNTIFS(Eventos!$A$2:$A$209,$A3,Eventos!$Q$2:$Q$209,"<>") -> 0
A4: EV03 | B4: Generales 3 | D4: El que pide plata | E4: =COUNTIFS(Eventos!$A$2:$A$209,$A4,Eventos!$H$2:$H$209,1) -> 2 | F4: =COUNTIF(Eventos!$A$2:$A$209,$A4) -> 2 | G4: =SUMIF(Eventos!$A$2:$A$209,$A4,Eventos!$K$2:$K$209) -> 0 | H4: =SUMIF(Eventos!$A$2:$A$209,$A4,Eventos!$L$2:$L$209) -> 0 | I4: =SUMIF(Eventos!$A$2:$A$209,$A4,Eventos!$M$2:$M$209) -> -12 | J4: =SUMIF(Eventos!$A$2:$A$209,$A4,Eventos!$N$2:$N$209) -> 12 | K4: =COUNTIFS(Eventos!$A$2:$A$209,$A4,Eventos!$Q$2:$Q$209,"<>") -> 0
A5: EV04 | B5: Generales 4 | D5: ¿Dónde vas a estudiar? | E5: =COUNTIFS(Eventos!$A$2:$A$209,$A5,Eventos!$H$2:$H$209,1) -> 3 | F5: =COUNTIF(Eventos!$A$2:$A$209,$A5) -> 3 | G5: =SUMIF(Eventos!$A$2:$A$209,$A5,Eventos!$K$2:$K$209) -> 0 | H5: =SUMIF(Eventos!$A$2:$A$209,$A5,Eventos!$L$2:$L$209) -> 12 | I5: =SUMIF(Eventos!$A$2:$A$209,$A5,Eventos!$M$2:$M$209) -> 0 | J5: =SUMIF(Eventos!$A$2:$A$209,$A5,Eventos!$N$2:$N$209) -> 0 | K5: =COUNTIFS(Eventos!$A$2:$A$209,$A5,Eventos!$Q$2:$Q$209,"<>") -> 0
A6: EV05 | B6: Generales 5 | D6: Trabajo de investigación | E6: =COUNTIFS(Eventos!$A$2:$A$209,$A6,Eventos!$H$2:$H$209,1) -> 2 | F6: =COUNTIF(Eventos!$A$2:$A$209,$A6) -> 2 | G6: =SUMIF(Eventos!$A$2:$A$209,$A6,Eventos!$K$2:$K$209) -> 0 | H6: =SUMIF(Eventos!$A$2:$A$209,$A6,Eventos!$L$2:$L$209) -> 10 | I6: =SUMIF(Eventos!$A$2:$A$209,$A6,Eventos!$M$2:$M$209) -> 12 | J6: =SUMIF(Eventos!$A$2:$A$209,$A6,Eventos!$N$2:$N$209) -> 0 | K6: =COUNTIFS(Eventos!$A$2:$A$209,$A6,Eventos!$Q$2:$Q$209,"<>") -> 0
A7: EV06 | B7: Generales 6 | D7: Clase muy embolante | E7: =COUNTIFS(Eventos!$A$2:$A$209,$A7,Eventos!$H$2:$H$209,1) -> 3 | F7: =COUNTIF(Eventos!$A$2:$A$209,$A7) -> 4 | G7: =SUMIF(Eventos!$A$2:$A$209,$A7,Eventos!$K$2:$K$209) -> -12 | H7: =SUMIF(Eventos!$A$2:$A$209,$A7,Eventos!$L$2:$L$209) -> 34 | I7: =SUMIF(Eventos!$A$2:$A$209,$A7,Eventos!$M$2:$M$209) -> -12 | J7: =SUMIF(Eventos!$A$2:$A$209,$A7,Eventos!$N$2:$N$209) -> 0 | K7: =COUNTIFS(Eventos!$A$2:$A$209,$A7,Eventos!$Q$2:$Q$209,"<>") -> 0
A8: EV07 | B8: Generales 7 | D8: El que no para de decir boludeces | E8: =COUNTIFS(Eventos!$A$2:$A$209,$A8,Eventos!$H$2:$H$209,1) -> 3 | F8: =COUNTIF(Eventos!$A$2:$A$209,$A8) -> 3 | G8: =SUMIF(Eventos!$A$2:$A$209,$A8,Eventos!$K$2:$K$209) -> 0 | H8: =SUMIF(Eventos!$A$2:$A$209,$A8,Eventos!$L$2:$L$209) -> 12 | I8: =SUMIF(Eventos!$A$2:$A$209,$A8,Eventos!$M$2:$M$209) -> -24 | J8: =SUMIF(Eventos!$A$2:$A$209,$A8,Eventos!$N$2:$N$209) -> 0 | K8: =COUNTIFS(Eventos!$A$2:$A$209,$A8,Eventos!$Q$2:$Q$209,"<>") -> 0
A9: EV08 | B9: Generales 8 | D9: ¿Por qué siguen acumulando? | E9: =COUNTIFS(Eventos!$A$2:$A$209,$A9,Eventos!$H$2:$H$209,1) -> 4 | F9: =COUNTIF(Eventos!$A$2:$A$209,$A9) -> 4 | G9: =SUMIF(Eventos!$A$2:$A$209,$A9,Eventos!$K$2:$K$209) -> 0 | H9: =SUMIF(Eventos!$A$2:$A$209,$A9,Eventos!$L$2:$L$209) -> -2 | I9: =SUMIF(Eventos!$A$2:$A$209,$A9,Eventos!$M$2:$M$209) -> 0 | J9: =SUMIF(Eventos!$A$2:$A$209,$A9,Eventos!$N$2:$N$209) -> 12 | K9: =COUNTIFS(Eventos!$A$2:$A$209,$A9,Eventos!$Q$2:$Q$209,"<>") -> 0
A10: EV09 | B10: Generales 9 | D10: El fan de Charles Manson | E10: =COUNTIFS(Eventos!$A$2:$A$209,$A10,Eventos!$H$2:$H$209,1) -> 3 | F10: =COUNTIF(Eventos!$A$2:$A$209,$A10) -> 3 | G10: =SUMIF(Eventos!$A$2:$A$209,$A10,Eventos!$K$2:$K$209) -> 0 | H10: =SUMIF(Eventos!$A$2:$A$209,$A10,Eventos!$L$2:$L$209) -> 0 | I10: =SUMIF(Eventos!$A$2:$A$209,$A10,Eventos!$M$2:$M$209) -> -12 | J10: =SUMIF(Eventos!$A$2:$A$209,$A10,Eventos!$N$2:$N$209) -> -22 | K10: =COUNTIFS(Eventos!$A$2:$A$209,$A10,Eventos!$Q$2:$Q$209,"<>") -> 2
A11: EV10 | B11: Generales 10 | D11: Final a las cinco de la tarde | E11: =COUNTIFS(Eventos!$A$2:$A$209,$A11,Eventos!$H$2:$H$209,1) -> 2 | F11: =COUNTIF(Eventos!$A$2:$A$209,$A11) -> 4 | G11: =SUMIF(Eventos!$A$2:$A$209,$A11,Eventos!$K$2:$K$209) -> 0 | H11: =SUMIF(Eventos!$A$2:$A$209,$A11,Eventos!$L$2:$L$209) -> -24 | I11: =SUMIF(Eventos!$A$2:$A$209,$A11,Eventos!$M$2:$M$209) -> 12 | J11: =SUMIF(Eventos!$A$2:$A$209,$A11,Eventos!$N$2:$N$209) -> 0 | K11: =COUNTIFS(Eventos!$A$2:$A$209,$A11,Eventos!$Q$2:$Q$209,"<>") -> 0
A12: EV11 | B12: Generales 11 | D12: El after y el Pity | E12: =COUNTIFS(Eventos!$A$2:$A$209,$A12,Eventos!$H$2:$H$209,1) -> 2 | F12: =COUNTIF(Eventos!$A$2:$A$209,$A12) -> 2 | G12: =SUMIF(Eventos!$A$2:$A$209,$A12,Eventos!$K$2:$K$209) -> 0 | H12: =SUMIF(Eventos!$A$2:$A$209,$A12,Eventos!$L$2:$L$209) -> 0 | I12: =SUMIF(Eventos!$A$2:$A$209,$A12,Eventos!$M$2:$M$209) -> 10 | J12: =SUMIF(Eventos!$A$2:$A$209,$A12,Eventos!$N$2:$N$209) -> 0 | K12: =COUNTIFS(Eventos!$A$2:$A$209,$A12,Eventos!$Q$2:$Q$209,"<>") -> 0
A13: EV12 | B13: Generales 12 | D13: La sala de radio | E13: =COUNTIFS(Eventos!$A$2:$A$209,$A13,Eventos!$H$2:$H$209,1) -> 2 | F13: =COUNTIF(Eventos!$A$2:$A$209,$A13) -> 2 | G13: =SUMIF(Eventos!$A$2:$A$209,$A13,Eventos!$K$2:$K$209) -> 0 | H13: =SUMIF(Eventos!$A$2:$A$209,$A13,Eventos!$L$2:$L$209) -> 0 | I13: =SUMIF(Eventos!$A$2:$A$209,$A13,Eventos!$M$2:$M$209) -> 12 | J13: =SUMIF(Eventos!$A$2:$A$209,$A13,Eventos!$N$2:$N$209) -> 0 | K13: =COUNTIFS(Eventos!$A$2:$A$209,$A13,Eventos!$Q$2:$Q$209,"<>") -> 0
... A35: EV34 | B35: Guita 2 | D35: El mega libro del titular | E35: =COUNTIFS(Eventos!$A$2:$A$209,$A35,Eventos!$H$2:$H$209,1) -> 3 | F35: =COUNTIF(Eventos!$A$2:$A$209,$A35) -> 4 | G35: =SUMIF(Eventos!$A$2:$A$209,$A35,Eventos!$K$2:$K$209) -> 44 | H35: =SUMIF(Eventos!$A$2:$A$209,$A35,Eventos!$L$2:$L$209) -> 0 | I35: =SUMIF(Eventos!$A$2:$A$209,$A35,Eventos!$M$2:$M$209) -> 0 | J35: =SUMIF(Eventos!$A$2:$A$209,$A35,Eventos!$N$2:$N$209) -> 0 | K35: =COUNTIFS(Eventos!$A$2:$A$209,$A35,Eventos!$Q$2:$Q$209,"<>") -> 0
A36: EV35 | B36: Guita 3 | C36: Mitad de carrera | D36: La campaña del candidato | E36: =COUNTIFS(Eventos!$A$2:$A$209,$A36,Eventos!$H$2:$H$209,1) -> 3 | F36: =COUNTIF(Eventos!$A$2:$A$209,$A36) -> 3 | G36: =SUMIF(Eventos!$A$2:$A$209,$A36,Eventos!$K$2:$K$209) -> 12 | H36: =SUMIF(Eventos!$A$2:$A$209,$A36,Eventos!$L$2:$L$209) -> 0 | I36: =SUMIF(Eventos!$A$2:$A$209,$A36,Eventos!$M$2:$M$209) -> 0 | J36: =SUMIF(Eventos!$A$2:$A$209,$A36,Eventos!$N$2:$N$209) -> 12 | K36: =COUNTIFS(Eventos!$A$2:$A$209,$A36,Eventos!$Q$2:$Q$209,"<>") -> 0
A37: EV36 | B37: Guita 4 | C37: Avanzado | D37: La beca y el despido | E37: =COUNTIFS(Eventos!$A$2:$A$209,$A37,Eventos!$H$2:$H$209,1) -> 3 | F37: =COUNTIF(Eventos!$A$2:$A$209,$A37) -> 3 | G37: =SUMIF(Eventos!$A$2:$A$209,$A37,Eventos!$K$2:$K$209) -> 0 | H37: =SUMIF(Eventos!$A$2:$A$209,$A37,Eventos!$L$2:$L$209) -> -12 | I37: =SUMIF(Eventos!$A$2:$A$209,$A37,Eventos!$M$2:$M$209) -> -12 | J37: =SUMIF(Eventos!$A$2:$A$209,$A37,Eventos!$N$2:$N$209) -> 0 | K37: =COUNTIFS(Eventos!$A$2:$A$209,$A37,Eventos!$Q$2:$Q$209,"<>") -> 0
A38: EV37 | B38: Guita 5 | D38: Prácticas educativas | E38: =COUNTIFS(Eventos!$A$2:$A$209,$A38,Eventos!$H$2:$H$209,1) -> 2 | F38: =COUNTIF(Eventos!$A$2:$A$209,$A38) -> 2 | G38: =SUMIF(Eventos!$A$2:$A$209,$A38,Eventos!$K$2:$K$209) -> 0 | H38: =SUMIF(Eventos!$A$2:$A$209,$A38,Eventos!$L$2:$L$209) -> 0 | I38: =SUMIF(Eventos!$A$2:$A$209,$A38,Eventos!$M$2:$M$209) -> 0 | J38: =SUMIF(Eventos!$A$2:$A$209,$A38,Eventos!$N$2:$N$209) -> 0 | K38: =COUNTIFS(Eventos!$A$2:$A$209,$A38,Eventos!$Q$2:$Q$209,"<>") -> 0
A39: EV38 | B39: Guita 6 | D39: 8 horas por $200.000 | E39: =COUNTIFS(Eventos!$A$2:$A$209,$A39,Eventos!$H$2:$H$209,1) -> 2 | F39: =COUNTIF(Eventos!$A$2:$A$209,$A39) -> 3 | G39: =SUMIF(Eventos!$A$2:$A$209,$A39,Eventos!$K$2:$K$209) -> 0 | H39: =SUMIF(Eventos!$A$2:$A$209,$A39,Eventos!$L$2:$L$209) -> 36 | I39: =SUMIF(Eventos!$A$2:$A$209,$A39,Eventos!$M$2:$M$209) -> 0 | J39: =SUMIF(Eventos!$A$2:$A$209,$A39,Eventos!$N$2:$N$209) -> 0 | K39: =COUNTIFS(Eventos!$A$2:$A$209,$A39,Eventos!$Q$2:$Q$209,"<>") -> 0
A40: EV39 | B40: Guita 7 | D40: No alcanza para nada | E40: =COUNTIFS(Eventos!$A$2:$A$209,$A40,Eventos!$H$2:$H$209,1) -> 3 | F40: =COUNTIF(Eventos!$A$2:$A$209,$A40) -> 3 | G40: =SUMIF(Eventos!$A$2:$A$209,$A40,Eventos!$K$2:$K$209) -> 22 | H40: =SUMIF(Eventos!$A$2:$A$209,$A40,Eventos!$L$2:$L$209) -> -22 | I40: =SUMIF(Eventos!$A$2:$A$209,$A40,Eventos!$M$2:$M$209) -> 12 | J40: =SUMIF(Eventos!$A$2:$A$209,$A40,Eventos!$N$2:$N$209) -> 0 | K40: =COUNTIFS(Eventos!$A$2:$A$209,$A40,Eventos!$Q$2:$Q$209,"<>") -> 1
A41: EV40 | B41: Guita 8 | D41: Becas de trabajo en el comedor | E41: =COUNTIFS(Eventos!$A$2:$A$209,$A41,Eventos!$H$2:$H$209,1) -> 3 | F41: =COUNTIF(Eventos!$A$2:$A$209,$A41) -> 3 | G41: =SUMIF(Eventos!$A$2:$A$209,$A41,Eventos!$K$2:$K$209) -> 44 | H41: =SUMIF(Eventos!$A$2:$A$209,$A41,Eventos!$L$2:$L$209) -> 0 | I41: =SUMIF(Eventos!$A$2:$A$209,$A41,Eventos!$M$2:$M$209) -> 0 | J41: =SUMIF(Eventos!$A$2:$A$209,$A41,Eventos!$N$2:$N$209) -> -22 | K41: =COUNTIFS(Eventos!$A$2:$A$209,$A41,Eventos!$Q$2:$Q$209,"<>") -> 0
A42: EV41 | B42: Guita 9 | D42: La plata de la nona | E42: =COUNTIFS(Eventos!$A$2:$A$209,$A42,Eventos!$H$2:$H$209,1) -> 2 | F42: =COUNTIF(Eventos!$A$2:$A$209,$A42) -> 2 | G42: =SUMIF(Eventos!$A$2:$A$209,$A42,Eventos!$K$2:$K$209) -> 0 | H42: =SUMIF(Eventos!$A$2:$A$209,$A42,Eventos!$L$2:$L$209) -> 10 | I42: =SUMIF(Eventos!$A$2:$A$209,$A42,Eventos!$M$2:$M$209) -> 22 | J42: =SUMIF(Eventos!$A$2:$A$209,$A42,Eventos!$N$2:$N$209) -> 0 | K42: =COUNTIFS(Eventos!$A$2:$A$209,$A42,Eventos!$Q$2:$Q$209,"<>") -> 0
A43: EV42 | B43: Guita 10 | D43: El que vende los parciales | E43: =COUNTIFS(Eventos!$A$2:$A$209,$A43,Eventos!$H$2:$H$209,1) -> 3 | F43: =COUNTIF(Eventos!$A$2:$A$209,$A43) -> 5 | G43: =SUMIF(Eventos!$A$2:$A$209,$A43,Eventos!$K$2:$K$209) -> -104 | H43: =SUMIF(Eventos!$A$2:$A$209,$A43,Eventos!$L$2:$L$209) -> -22 | I43: =SUMIF(Eventos!$A$2:$A$209,$A43,Eventos!$M$2:$M$209) -> -24 | J43: =SUMIF(Eventos!$A$2:$A$209,$A43,Eventos!$N$2:$N$209) -> -24 | K43: =COUNTIFS(Eventos!$A$2:$A$209,$A43,Eventos!$Q$2:$Q$209,"<>") -> 0
A44: EV43 | B44: Conocimiento 1 | C44: Mitad de carrera | D44: La bicicleta al costado de las vías | E44: =COUNTIFS(Eventos!$A$2:$A$209,$A44,Eventos!$H$2:$H$209,1) -> 2 | F44: =COUNTIF(Eventos!$A$2:$A$209,$A44) -> 3 | G44: =SUMIF(Eventos!$A$2:$A$209,$A44,Eventos!$K$2:$K$209) -> -12 | H44: =SUMIF(Eventos!$A$2:$A$209,$A44,Eventos!$L$2:$L$209) -> 22 | I44: =SUMIF(Eventos!$A$2:$A$209,$A44,Eventos!$M$2:$M$209) -> 10 | J44: =SUMIF(Eventos!$A$2:$A$209,$A44,Eventos!$N$2:$N$209) -> 22 | K44: =COUNTIFS(Eventos!$A$2:$A$209,$A44,Eventos!$Q$2:$Q$209,"<>") -> 1
A45: EV44 | B45: Conocimiento 2 | D45: El porro antes del final | E45: =COUNTIFS(Eventos!$A$2:$A$209,$A45,Eventos!$H$2:$H$209,1) -> 2 | F45: =COUNTIF(Eventos!$A$2:$A$209,$A45) -> 4 | G45: =SUMIF(Eventos!$A$2:$A$209,$A45,Eventos!$K$2:$K$209) -> 0 | H45: =SUMIF(Eventos!$A$2:$A$209,$A45,Eventos!$L$2:$L$209) -> 32 | I45: =SUMIF(Eventos!$A$2:$A$209,$A45,Eventos!$M$2:$M$209) -> -12 | J45: =SUMIF(Eventos!$A$2:$A$209,$A45,Eventos!$N$2:$N$209) -> 0 | K45: =COUNTIFS(Eventos!$A$2:$A$209,$A45,Eventos!$Q$2:$Q$209,"<>") -> 0
A46: EV45 | B46: Conocimiento 3 | D46: El autor del que nadie habla | E46: =COUNTIFS(Eventos!$A$2:$A$209,$A46,Eventos!$H$2:$H$209,1) -> 3 | F46: =COUNTIF(Eventos!$A$2:$A$209,$A46) -> 5 | G46: =SUMIF(Eventos!$A$2:$A$209,$A46,Eventos!$K$2:$K$209) -> 0 | H46: =SUMIF(Eventos!$A$2:$A$209,$A46,Eventos!$L$2:$L$209) -> 24 | I46: =SUMIF(Eventos!$A$2:$A$209,$A46,Eventos!$M$2:$M$209) -> 12 | J46: =SUMIF(Eventos!$A$2:$A$209,$A46,Eventos!$N$2:$N$209) -> 24 | K46: =COUNTIFS(Eventos!$A$2:$A$209,$A46,Eventos!$Q$2:$Q$209,"<>") -> 0
A47: EV46 | B47: Conocimiento 4 | D47: La monografía que no pediste | E47: =COUNTIFS(Eventos!$A$2:$A$209,$A47,Eventos!$H$2:$H$209,1) -> 3 | F47: =COUNTIF(Eventos!$A$2:$A$209,$A47) -> 4 | G47: =SUMIF(Eventos!$A$2:$A$209,$A47,Eventos!$K$2:$K$209) -> 0 | H47: =SUMIF(Eventos!$A$2:$A$209,$A47,Eventos!$L$2:$L$209) -> -24 | I47: =SUMIF(Eventos!$A$2:$A$209,$A47,Eventos!$M$2:$M$209) -> 12 | J47: =SUMIF(Eventos!$A$2:$A$209,$A47,Eventos!$N$2:$N$209) -> -12 | K47: =COUNTIFS(Eventos!$A$2:$A$209,$A47,Eventos!$Q$2:$Q$209,"<>") -> 0
A48: EV47 | B48: Conocimiento 5 | D48: Cuatro horas de teórico y una lija tremenda | E48: =COUNTIFS(Eventos!$A$2:$A$209,$A48,Eventos!$H$2:$H$209,1) -> 3 | F48: =COUNTIF(Eventos!$A$2:$A$209,$A48) -> 4 | G48: =SUMIF(Eventos!$A$2:$A$209,$A48,Eventos!$K$2:$K$209) -> 22 | H48: =SUMIF(Eventos!$A$2:$A$209,$A48,Eventos!$L$2:$L$209) -> -12 | I48: =SUMIF(Eventos!$A$2:$A$209,$A48,Eventos!$M$2:$M$209) -> 12 | J48: =SUMIF(Eventos!$A$2:$A$209,$A48,Eventos!$N$2:$N$209) -> 24 | K48: =COUNTIFS(Eventos!$A$2:$A$209,$A48,Eventos!$Q$2:$Q$209,"<>") -> 1
A49: EV48 | B49: Conocimiento 6 | D49: El pelado de teoría política | E49: =COUNTIFS(Eventos!$A$2:$A$209,$A49,Eventos!$H$2:$H$209,1) -> 4 | F49: =COUNTIF(Eventos!$A$2:$A$209,$A49) -> 4 | G49: =SUMIF(Eventos!$A$2:$A$209,$A49,Eventos!$K$2:$K$209) -> -12 | H49: =SUMIF(Eventos!$A$2:$A$209,$A49,Eventos!$L$2:$L$209) -> 12 | I49: =SUMIF(Eventos!$A$2:$A$209,$A49,Eventos!$M$2:$M$209) -> 12 | J49: =SUMIF(Eventos!$A$2:$A$209,$A49,Eventos!$N$2:$N$209) -> 22 | K49: =COUNTIFS(Eventos!$A$2:$A$209,$A49,Eventos!$Q$2:$Q$209,"<>") -> 1
A50: EV49 | B50: Conocimiento 7 | D50: El trámite imposible | E50: =COUNTIFS(Eventos!$A$2:$A$209,$A50,Eventos!$H$2:$H$209,1) -> 3 | F50: =COUNTIF(Eventos!$A$2:$A$209,$A50) -> 3 | G50: =SUMIF(Eventos!$A$2:$A$209,$A50,Eventos!$K$2:$K$209) -> 0 | H50: =SUMIF(Eventos!$A$2:$A$209,$A50,Eventos!$L$2:$L$209) -> -50 | I50: =SUMIF(Eventos!$A$2:$A$209,$A50,Eventos!$M$2:$M$209) -> 12 | J50: =SUMIF(Eventos!$A$2:$A$209,$A50,Eventos!$N$2:$N$209) -> -25 | K50: =COUNTIFS(Eventos!$A$2:$A$209,$A50,Eventos!$Q$2:$Q$209,"<>") -> 0
A51: EV50 | B51: Fama 1 | D51: Vinieron a tapar los murales | E51: =COUNTIFS(Eventos!$A$2:$A$209,$A51,Eventos!$H$2:$H$209,1) -> 3 | F51: =COUNTIF(Eventos!$A$2:$A$209,$A51) -> 3 | G51: =SUMIF(Eventos!$A$2:$A$209,$A51,Eventos!$K$2:$K$209) -> 0 | H51: =SUMIF(Eventos!$A$2:$A$209,$A51,Eventos!$L$2:$L$209) -> -12 | I51: =SUMIF(Eventos!$A$2:$A$209,$A51,Eventos!$M$2:$M$209) -> 12 | J51: =SUMIF(Eventos!$A$2:$A$209,$A51,Eventos!$N$2:$N$209) -> 24 | K51: =COUNTIFS(Eventos!$A$2:$A$209,$A51,Eventos!$Q$2:$Q$209,"<>") -> 1
A52: EV51 | B52: Fama 2 | D52: Los noteros | E52: =COUNTIFS(Eventos!$A$2:$A$209,$A52,Eventos!$H$2:$H$209,1) -> 2 | F52: =COUNTIF(Eventos!$A$2:$A$209,$A52) -> 3 | G52: =SUMIF(Eventos!$A$2:$A$209,$A52,Eventos!$K$2:$K$209) -> 0 | H52: =SUMIF(Eventos!$A$2:$A$209,$A52,Eventos!$L$2:$L$209) -> 0 | I52: =SUMIF(Eventos!$A$2:$A$209,$A52,Eventos!$M$2:$M$209) -> 24 | J52: =SUMIF(Eventos!$A$2:$A$209,$A52,Eventos!$N$2:$N$209) -> 0 | K52: =COUNTIFS(Eventos!$A$2:$A$209,$A52,Eventos!$Q$2:$Q$209,"<>") -> 0
A53: EV52 | B53: Fama 3 | D53: El día de la expulsión | E53: =COUNTIFS(Eventos!$A$2:$A$209,$A53,Eventos!$H$2:$H$209,1) -> 3 | F53: =COUNTIF(Eventos!$A$2:$A$209,$A53) -> 3 | G53: =SUMIF(Eventos!$A$2:$A$209,$A53,Eventos!$K$2:$K$209) -> 0 | H53: =SUMIF(Eventos!$A$2:$A$209,$A53,Eventos!$L$2:$L$209) -> 0 | I53: =SUMIF(Eventos!$A$2:$A$209,$A53,Eventos!$M$2:$M$209) -> 22 | J53: =SUMIF(Eventos!$A$2:$A$209,$A53,Eventos!$N$2:$N$209) -> 0 | K53: =COUNTIFS(Eventos!$A$2:$A$209,$A53,Eventos!$Q$2:$Q$209,"<>") -> 1
A54: EV53 | B54: Fama 4 | D54: El pucho de la salida | E54: =COUNTIFS(Eventos!$A$2:$A$209,$A54,Eventos!$H$2:$H$209,1) -> 2 | F54: =COUNTIF(Eventos!$A$2:$A$209,$A54) -> 2 | G54: =SUMIF(Eventos!$A$2:$A$209,$A54,Eventos!$K$2:$K$209) -> 0 | H54: =SUMIF(Eventos!$A$2:$A$209,$A54,Eventos!$L$2:$L$209) -> 0 | I54: =SUMIF(Eventos!$A$2:$A$209,$A54,Eventos!$M$2:$M$209) -> 22 | J54: =SUMIF(Eventos!$A$2:$A$209,$A54,Eventos!$N$2:$N$209) -> 12 | K54: =COUNTIFS(Eventos!$A$2:$A$209,$A54,Eventos!$Q$2:$Q$209,"<>") -> 0
A55: EV54 | B55: Fama 5 | D55: Dejar una huella | E55: =COUNTIFS(Eventos!$A$2:$A$209,$A55,Eventos!$H$2:$H$209,1) -> 3 | F55: =COUNTIF(Eventos!$A$2:$A$209,$A55) -> 3 | G55: =SUMIF(Eventos!$A$2:$A$209,$A55,Eventos!$K$2:$K$209) -> 0 | H55: =SUMIF(Eventos!$A$2:$A$209,$A55,Eventos!$L$2:$L$209) -> 12 | I55: =SUMIF(Eventos!$A$2:$A$209,$A55,Eventos!$M$2:$M$209) -> -12 | J55: =SUMIF(Eventos!$A$2:$A$209,$A55,Eventos!$N$2:$N$209) -> 0 | K55: =COUNTIFS(Eventos!$A$2:$A$209,$A55,Eventos!$Q$2:$Q$209,"<>") -> 0
A56: EV55 | B56: Fama 6 | D56: ¿Te anotás para hablar? | E56: =COUNTIFS(Eventos!$A$2:$A$209,$A56,Eventos!$H$2:$H$209,1) -> 2 | F56: =COUNTIF(Eventos!$A$2:$A$209,$A56) -> 3 | G56: =SUMIF(Eventos!$A$2:$A$209,$A56,Eventos!$K$2:$K$209) -> 0 | H56: =SUMIF(Eventos!$A$2:$A$209,$A56,Eventos!$L$2:$L$209) -> -24 | I56: =SUMIF(Eventos!$A$2:$A$209,$A56,Eventos!$M$2:$M$209) -> 22 | J56: =SUMIF(Eventos!$A$2:$A$209,$A56,Eventos!$N$2:$N$209) -> -12 | K56: =COUNTIFS(Eventos!$A$2:$A$209,$A56,Eventos!$Q$2:$Q$209,"<>") -> 0
... A63: EV62 | B63: Política 6 | D63: Hacer pasadas | E63: =COUNTIFS(Eventos!$A$2:$A$209,$A63,Eventos!$H$2:$H$209,1) -> 3 | F63: =COUNTIF(Eventos!$A$2:$A$209,$A63) -> 3 | G63: =SUMIF(Eventos!$A$2:$A$209,$A63,Eventos!$K$2:$K$209) -> 0 | H63: =SUMIF(Eventos!$A$2:$A$209,$A63,Eventos!$L$2:$L$209) -> 0 | I63: =SUMIF(Eventos!$A$2:$A$209,$A63,Eventos!$M$2:$M$209) -> 12 | J63: =SUMIF(Eventos!$A$2:$A$209,$A63,Eventos!$N$2:$N$209) -> -12 | K63: =COUNTIFS(Eventos!$A$2:$A$209,$A63,Eventos!$Q$2:$Q$209,"<>") -> 0
A64: EV63 | B64: Historia 1 | C64: Ingresante | D64: La revolución social tiene que llegar | E64: =COUNTIFS(Eventos!$A$2:$A$209,$A64,Eventos!$H$2:$H$209,1) -> 2 | F64: =COUNTIF(Eventos!$A$2:$A$209,$A64) -> 2 | G64: =SUMIF(Eventos!$A$2:$A$209,$A64,Eventos!$K$2:$K$209) -> 12 | H64: =SUMIF(Eventos!$A$2:$A$209,$A64,Eventos!$L$2:$L$209) -> 0 | I64: =SUMIF(Eventos!$A$2:$A$209,$A64,Eventos!$M$2:$M$209) -> 12 | J64: =SUMIF(Eventos!$A$2:$A$209,$A64,Eventos!$N$2:$N$209) -> 12 | K64: =COUNTIFS(Eventos!$A$2:$A$209,$A64,Eventos!$Q$2:$Q$209,"<>") -> 0
A65: EV64 | B65: Historia 2 | C65: Ingresante | D65: Protesta en la puerta de OLGA | E65: =COUNTIFS(Eventos!$A$2:$A$209,$A65,Eventos!$H$2:$H$209,1) -> 2 | F65: =COUNTIF(Eventos!$A$2:$A$209,$A65) -> 3 | G65: =SUMIF(Eventos!$A$2:$A$209,$A65,Eventos!$K$2:$K$209) -> 0 | H65: =SUMIF(Eventos!$A$2:$A$209,$A65,Eventos!$L$2:$L$209) -> -22 | I65: =SUMIF(Eventos!$A$2:$A$209,$A65,Eventos!$M$2:$M$209) -> 12 | J65: =SUMIF(Eventos!$A$2:$A$209,$A65,Eventos!$N$2:$N$209) -> 12 | K65: =COUNTIFS(Eventos!$A$2:$A$209,$A65,Eventos!$Q$2:$Q$209,"<>") -> 0
A66: EV65 | B66: Historia 3 | C66: Ingresante | D66: La juntada intelectual | E66: =COUNTIFS(Eventos!$A$2:$A$209,$A66,Eventos!$H$2:$H$209,1) -> 2 | F66: =COUNTIF(Eventos!$A$2:$A$209,$A66) -> 4 | G66: =SUMIF(Eventos!$A$2:$A$209,$A66,Eventos!$K$2:$K$209) -> -22 | H66: =SUMIF(Eventos!$A$2:$A$209,$A66,Eventos!$L$2:$L$209) -> 0 | I66: =SUMIF(Eventos!$A$2:$A$209,$A66,Eventos!$M$2:$M$209) -> -12 | J66: =SUMIF(Eventos!$A$2:$A$209,$A66,Eventos!$N$2:$N$209) -> 12 | K66: =COUNTIFS(Eventos!$A$2:$A$209,$A66,Eventos!$Q$2:$Q$209,"<>") -> 0
A67: EV66 | B67: Historia 4 | C67: Intermedio | D67: La interna por el movimiento | E67: =COUNTIFS(Eventos!$A$2:$A$209,$A67,Eventos!$H$2:$H$209,1) -> 2 | F67: =COUNTIF(Eventos!$A$2:$A$209,$A67) -> 3 | G67: =SUMIF(Eventos!$A$2:$A$209,$A67,Eventos!$K$2:$K$209) -> 0 | H67: =SUMIF(Eventos!$A$2:$A$209,$A67,Eventos!$L$2:$L$209) -> 24 | I67: =SUMIF(Eventos!$A$2:$A$209,$A67,Eventos!$M$2:$M$209) -> 22 | J67: =SUMIF(Eventos!$A$2:$A$209,$A67,Eventos!$N$2:$N$209) -> 9 | K67: =COUNTIFS(Eventos!$A$2:$A$209,$A67,Eventos!$Q$2:$Q$209,"<>") -> 0
A68: EV67 | B68: Historia 5 | C68: Avanzado | D68: ¿A quién promocionás? | E68: =COUNTIFS(Eventos!$A$2:$A$209,$A68,Eventos!$H$2:$H$209,1) -> 2 | F68: =COUNTIF(Eventos!$A$2:$A$209,$A68) -> 2 | G68: =SUMIF(Eventos!$A$2:$A$209,$A68,Eventos!$K$2:$K$209) -> 22 | H68: =SUMIF(Eventos!$A$2:$A$209,$A68,Eventos!$L$2:$L$209) -> 0 | I68: =SUMIF(Eventos!$A$2:$A$209,$A68,Eventos!$M$2:$M$209) -> -12 | J68: =SUMIF(Eventos!$A$2:$A$209,$A68,Eventos!$N$2:$N$209) -> -34 | K68: =COUNTIFS(Eventos!$A$2:$A$209,$A68,Eventos!$Q$2:$Q$209,"<>") -> 0
D69: TOTAL | E69: =SUM(E2:E68) -> 177 | F69: =SUM(F2:F68) -> 208 | G69: =SUM(G2:G68) -> 30 | H69: =SUM(H2:H68) -> 40 | I69: =SUM(I2:I68) -> 24 | J69: =SUM(J2:J68) -> 46 | K69: =SUM(K2:K68) -> 22
